{
  "indexes": [
    {
      "collectionGroup": "employees",
      "queryScope": "COLLECTION",
      "fields": [
        { "fieldPath": "tenantId", "order": "ASCENDING" },
        { "fieldPath": "lastName",  "order": "ASCENDING" }
      ]
    },
    {
      "collectionGroup": "employees",
      "queryScope": "COLLECTION",
      "fields": [
        { "fieldPath": "storeId",  "order": "ASCENDING" },
        { "fieldPath": "hireDate", "order": "DESCENDING" }
      ]
    },
    {
      "collectionGroup": "employees",
      "queryScope": "COLLECTION",
      "fields": [
        { "fieldPath": "storeId", "order": "ASCENDING" },
        { "fieldPath": "role",    "order": "ASCENDING" }
      ]
    },
    {
      "collectionGroup": "employees",
      "queryScope": "COLLECTION",
      "fields": [
        { "fieldPath": "isActive", "order": "ASCENDING" },
        { "fieldPath": "tenantId", "order": "ASCENDING" }
      ]
    },
    {
      "collectionGroup": "attendanceRecords",
      "queryScope": "COLLECTION",
      "fields": [
        { "fieldPath": "employeeId", "order": "ASCENDING" },
        { "fieldPath": "date", "order": "DESCENDING" }
      ]
    },
    {
      "collectionGroup": "attendanceRecords",
      "queryScope": "COLLECTION",
      "fields": [
        { "fieldPath": "storeId", "order": "ASCENDING" },
        { "fieldPath": "date", "order": "ASCENDING" },
        { "fieldPath": "type", "order": "ASCENDING" }
      ]
    },
    {
      "collectionGroup": "attendanceRecords",
      "queryScope": "COLLECTION",
      "fields": [
        { "fieldPath": "tenantId", "order": "ASCENDING" },
        { "fieldPath": "storeId", "order": "ASCENDING" },
        { "fieldPath": "date", "order": "DESCENDING" }
      ]
    },
    {
      "collectionGroup": "schedules",
      "queryScope": "COLLECTION",
      "fields": [
        { "fieldPath": "employeeId", "order": "ASCENDING" },
        { "fieldPath": "date", "order": "ASCENDING" }
      ]
    },
    {
      "collectionGroup": "schedules",
      "queryScope": "COLLECTION",
      "fields": [
        { "fieldPath": "storeId", "order": "ASCENDING" },
        { "fieldPath": "date", "order": "ASCENDING" }
      ]
    },
    {
      "collectionGroup": "orders",
      "queryScope": "COLLECTION",
      "fields": [
        { "fieldPath": "tenantId", "order": "ASCENDING" },
        { "fieldPath": "createdAt", "order": "DESCENDING" }
      ]
    },
    {
      "collectionGroup": "orders",
      "queryScope": "COLLECTION",
      "fields": [
        { "fieldPath": "tenantId", "order": "ASCENDING" },
        { "fieldPath": "storeId", "order": "ASCENDING" },
        { "fieldPath": "createdAt", "order": "DESCENDING" }
      ]
    },
    {
      "collectionGroup": "orders",
      "queryScope": "COLLECTION",
      "fields": [
        { "fieldPath": "tenantId", "order": "ASCENDING" },
        { "fieldPath": "status", "order": "ASCENDING" },
        { "fieldPath": "createdAt", "order": "DESCENDING" }
      ]
    },
    {
      "collectionGroup": "orders",
      "queryScope": "COLLECTION",
      "fields": [
        { "fieldPath": "tenantId", "order": "ASCENDING" },
        { "fieldPath": "storeId", "order": "ASCENDING" },
        { "fieldPath": "status", "order": "ASCENDING" },
        { "fieldPath": "createdAt", "order": "DESCENDING" }
      ]
    },
    {
      "collectionGroup": "orders",
      "queryScope": "COLLECTION",
      "fields": [
        { "fieldPath": "tenantId", "order": "ASCENDING" },
        { "fieldPath": "customerId", "order": "ASCENDING" },
        { "fieldPath": "createdAt", "order": "DESCENDING" }
      ]
    },
    {
      "collectionGroup": "employees",
      "queryScope": "COLLECTION",
      "fields": [
        { "fieldPath": "tenantId", "order": "ASCENDING" },
        { "fieldPath": "storeId", "order": "ASCENDING" },
        { "fieldPath": "employmentInfo.roleLevel", "order": "ASCENDING" }
      ]
    },
    {
      "collectionGroup": "employees",
      "queryScope": "COLLECTION",
      "fields": [
        { "fieldPath": "tenantId", "order": "ASCENDING" },
        { "fieldPath": "workingStatus.isActive", "order": "ASCENDING" },
        { "fieldPath": "employmentInfo.hireDate", "order": "DESCENDING" }
      ]
    },
    {
      "collectionGroup": "employees",
      "queryScope": "COLLECTION",
      "fields": [
        { "fieldPath": "storeId", "order": "ASCENDING" },
        { "fieldPath": "workingStatus.isActive", "order": "ASCENDING" },
        { "fieldPath": "lastName", "order": "ASCENDING" }
      ]
    },
    {
      "collectionGroup": "stores",
      "queryScope": "COLLECTION",
      "fields": [
        { "fieldPath": "tenantId", "order": "ASCENDING" },
        { "fieldPath": "isActive", "order": "ASCENDING" },
        { "fieldPath": "storeName", "order": "ASCENDING" }
      ]
    },
    {
      "collectionGroup": "stores",
      "queryScope": "COLLECTION",
      "fields": [
        { "fieldPath": "tenantId", "order": "ASCENDING" },
        { "fieldPath": "location.lat", "order": "ASCENDING" },
        { "fieldPath": "location.lng", "order": "ASCENDING" }
      ]
    },
    {
      "collectionGroup": "roles",
      "queryScope": "COLLECTION",
      "fields": [
        { "fieldPath": "tenantId", "order": "ASCENDING" },
        { "fieldPath": "level", "order": "ASCENDING" }
      ]
    },
    {
      "collectionGroup": "roles",
      "queryScope": "COLLECTION",
      "fields": [
        { "fieldPath": "isSystemRole", "order": "ASCENDING" },
        { "fieldPath": "level", "order": "ASCENDING" }
      ]
    },
    {
      "collectionGroup": "auditLogs",
      "queryScope": "COLLECTION",
      "fields": [
        { "fieldPath": "tenantId", "order": "ASCENDING" },
        { "fieldPath": "timestamp", "order": "DESCENDING" }
      ]
    },
    {
      "collectionGroup": "auditLogs",
      "queryScope": "COLLECTION",
      "fields": [
        { "fieldPath": "tenantId", "order": "ASCENDING" },
        { "fieldPath": "storeId", "order": "ASCENDING" },
        { "fieldPath": "timestamp", "order": "DESCENDING" }
      ]
    },
    {
      "collectionGroup": "auditLogs",
      "queryScope": "COLLECTION",
      "fields": [
        { "fieldPath": "tenantId", "order": "ASCENDING" },
        { "fieldPath": "userId", "order": "ASCENDING" },
        { "fieldPath": "timestamp", "order": "DESCENDING" }
      ]
    },
    {
      "collectionGroup": "auditLogs",
      "queryScope": "COLLECTION",
      "fields": [
        { "fieldPath": "tenantId", "order": "ASCENDING" },
        { "fieldPath": "action", "order": "ASCENDING" },
        { "fieldPath": "timestamp", "order": "DESCENDING" }
      ]
    },
    {
      "collectionGroup": "auditLogs",
      "queryScope": "COLLECTION",
      "fields": [
        { "fieldPath": "targetEntityType", "order": "ASCENDING" },
        { "fieldPath": "targetEntityId", "order": "ASCENDING" },
        { "fieldPath": "timestamp", "order": "DESCENDING" }
      ]
    },
    {
      "collectionGroup": "auditLogs",
      "queryScope": "COLLECTION",
      "fields": [
        { "fieldPath": "tenantId", "order": "ASCENDING" },
        { "fieldPath": "status", "order": "ASCENDING" },
        { "fieldPath": "timestamp", "order": "DESCENDING" }
      ]
    }
  ],
  "fieldOverrides": []
} 